Metadata-Version: 2.2
Name: git_well
Version: 0.2.4
Summary: The git_well module
Home-page: https://github.com/Erotemic/git_well
Author: Jon Crall
Author-email: erotemic@gmail.com
License: Apache 2
Classifier: Development Status :: 1 - Planning
Classifier: Intended Audience :: Developers
Classifier: Topic :: Software Development :: Libraries :: Python Modules
Classifier: Topic :: Utilities
Classifier: License :: OSI Approved :: Apache Software License
Classifier: Programming Language :: Python :: 3.7
Classifier: Programming Language :: Python :: 3.8
Classifier: Programming Language :: Python :: 3.9
Classifier: Programming Language :: Python :: 3.10
Classifier: Programming Language :: Python :: 3.11
Classifier: Programming Language :: Python :: 3.12
Classifier: Programming Language :: Python :: 3.13
Requires-Python: >=3.7
Requires-Dist: ubelt>=1.3.3
Requires-Dist: scriptconfig>=0.7.10; python_version >= "3.6"
Requires-Dist: rich>=12.4.4; python_version >= "3.8"
Requires-Dist: rich>=11.2.0; python_version < "3.8" and python_version >= "3.6"
Requires-Dist: git-python>=1.0.0; python_version >= "2.7"
Requires-Dist: packaging>=21.3
Requires-Dist: networkx>=2.8; python_version < "4.0" and python_version >= "3.11"
Requires-Dist: networkx>=2.7; python_version < "3.11" and python_version >= "3.8"
Requires-Dist: networkx>=2.6.2; python_version < "3.8" and python_version >= "3.7"
Requires-Dist: networkx<=2.5.1,>=2.2.0; python_version < "3.7.0" and python_version >= "3.6.0"
Provides-Extra: all
Requires-Dist: ubelt>=1.3.3; extra == "all"
Requires-Dist: scriptconfig>=0.7.10; python_version >= "3.6" and extra == "all"
Requires-Dist: rich>=12.4.4; python_version >= "3.8" and extra == "all"
Requires-Dist: rich>=11.2.0; (python_version < "3.8" and python_version >= "3.6") and extra == "all"
Requires-Dist: git-python>=1.0.0; python_version >= "2.7" and extra == "all"
Requires-Dist: packaging>=21.3; extra == "all"
Requires-Dist: networkx>=2.8; (python_version < "4.0" and python_version >= "3.11") and extra == "all"
Requires-Dist: networkx>=2.7; (python_version < "3.11" and python_version >= "3.8") and extra == "all"
Requires-Dist: networkx>=2.6.2; (python_version < "3.8" and python_version >= "3.7") and extra == "all"
Requires-Dist: networkx<=2.5.1,>=2.2.0; (python_version < "3.7.0" and python_version >= "3.6.0") and extra == "all"
Requires-Dist: xdoctest>=1.1.3; extra == "all"
Requires-Dist: pytest>=6.2.5; python_version >= "3.10.0" and extra == "all"
Requires-Dist: pytest>=4.6.0; (python_version < "3.10.0" and python_version >= "3.7.0") and extra == "all"
Requires-Dist: pytest>=4.6.0; (python_version < "3.7.0" and python_version >= "3.6.0") and extra == "all"
Requires-Dist: pytest<=6.1.2,>=4.6.0; (python_version < "3.6.0" and python_version >= "3.5.0") and extra == "all"
Requires-Dist: pytest<=4.6.11,>=4.6.0; (python_version < "3.5.0" and python_version >= "3.4.0") and extra == "all"
Requires-Dist: pytest<=4.6.11,>=4.6.0; (python_version < "2.8.0" and python_version >= "2.7.0") and extra == "all"
Requires-Dist: pytest-cov>=3.0.0; python_version >= "3.6.0" and extra == "all"
Requires-Dist: pytest-cov>=2.9.0; (python_version < "3.6.0" and python_version >= "3.5.0") and extra == "all"
Requires-Dist: pytest-cov>=2.8.1; (python_version < "3.5.0" and python_version >= "3.4.0") and extra == "all"
Requires-Dist: pytest-cov>=2.8.1; (python_version < "2.8.0" and python_version >= "2.7.0") and extra == "all"
Requires-Dist: pytest-timeout>=1.4.2; extra == "all"
Requires-Dist: coverage>=6.1.1; python_version >= "3.10" and extra == "all"
Requires-Dist: coverage>=5.3.1; (python_version < "3.10" and python_version >= "3.9") and extra == "all"
Requires-Dist: coverage>=6.1.1; (python_version < "3.9" and python_version >= "3.8") and extra == "all"
Requires-Dist: coverage>=6.1.1; (python_version < "3.8" and python_version >= "3.7") and extra == "all"
Requires-Dist: coverage>=6.1.1; (python_version < "3.7" and python_version >= "3.6") and extra == "all"
Requires-Dist: coverage>=5.3.1; (python_version < "3.6" and python_version >= "3.5") and extra == "all"
Requires-Dist: coverage>=4.3.4; (python_version < "3.5" and python_version >= "3.4") and extra == "all"
Requires-Dist: coverage>=5.3.1; (python_version < "3.4" and python_version >= "2.7") and extra == "all"
Requires-Dist: coverage>=4.5; (python_version < "2.7" and python_version >= "2.6") and extra == "all"
Requires-Dist: argcomplete>=1.0; extra == "all"
Requires-Dist: rich_argparse>=1.1.0; python_version >= "3.7" and extra == "all"
Provides-Extra: runtime
Requires-Dist: ubelt>=1.3.3; extra == "runtime"
Requires-Dist: scriptconfig>=0.7.10; python_version >= "3.6" and extra == "runtime"
Requires-Dist: rich>=12.4.4; python_version >= "3.8" and extra == "runtime"
Requires-Dist: rich>=11.2.0; (python_version < "3.8" and python_version >= "3.6") and extra == "runtime"
Requires-Dist: git-python>=1.0.0; python_version >= "2.7" and extra == "runtime"
Requires-Dist: packaging>=21.3; extra == "runtime"
Requires-Dist: networkx>=2.8; (python_version < "4.0" and python_version >= "3.11") and extra == "runtime"
Requires-Dist: networkx>=2.7; (python_version < "3.11" and python_version >= "3.8") and extra == "runtime"
Requires-Dist: networkx>=2.6.2; (python_version < "3.8" and python_version >= "3.7") and extra == "runtime"
Requires-Dist: networkx<=2.5.1,>=2.2.0; (python_version < "3.7.0" and python_version >= "3.6.0") and extra == "runtime"
Provides-Extra: tests
Requires-Dist: xdoctest>=1.1.3; extra == "tests"
Requires-Dist: pytest>=6.2.5; python_version >= "3.10.0" and extra == "tests"
Requires-Dist: pytest>=4.6.0; (python_version < "3.10.0" and python_version >= "3.7.0") and extra == "tests"
Requires-Dist: pytest>=4.6.0; (python_version < "3.7.0" and python_version >= "3.6.0") and extra == "tests"
Requires-Dist: pytest<=6.1.2,>=4.6.0; (python_version < "3.6.0" and python_version >= "3.5.0") and extra == "tests"
Requires-Dist: pytest<=4.6.11,>=4.6.0; (python_version < "3.5.0" and python_version >= "3.4.0") and extra == "tests"
Requires-Dist: pytest<=4.6.11,>=4.6.0; (python_version < "2.8.0" and python_version >= "2.7.0") and extra == "tests"
Requires-Dist: pytest-cov>=3.0.0; python_version >= "3.6.0" and extra == "tests"
Requires-Dist: pytest-cov>=2.9.0; (python_version < "3.6.0" and python_version >= "3.5.0") and extra == "tests"
Requires-Dist: pytest-cov>=2.8.1; (python_version < "3.5.0" and python_version >= "3.4.0") and extra == "tests"
Requires-Dist: pytest-cov>=2.8.1; (python_version < "2.8.0" and python_version >= "2.7.0") and extra == "tests"
Requires-Dist: pytest-timeout>=1.4.2; extra == "tests"
Requires-Dist: coverage>=6.1.1; python_version >= "3.10" and extra == "tests"
Requires-Dist: coverage>=5.3.1; (python_version < "3.10" and python_version >= "3.9") and extra == "tests"
Requires-Dist: coverage>=6.1.1; (python_version < "3.9" and python_version >= "3.8") and extra == "tests"
Requires-Dist: coverage>=6.1.1; (python_version < "3.8" and python_version >= "3.7") and extra == "tests"
Requires-Dist: coverage>=6.1.1; (python_version < "3.7" and python_version >= "3.6") and extra == "tests"
Requires-Dist: coverage>=5.3.1; (python_version < "3.6" and python_version >= "3.5") and extra == "tests"
Requires-Dist: coverage>=4.3.4; (python_version < "3.5" and python_version >= "3.4") and extra == "tests"
Requires-Dist: coverage>=5.3.1; (python_version < "3.4" and python_version >= "2.7") and extra == "tests"
Requires-Dist: coverage>=4.5; (python_version < "2.7" and python_version >= "2.6") and extra == "tests"
Provides-Extra: optional
Requires-Dist: argcomplete>=1.0; extra == "optional"
Requires-Dist: rich_argparse>=1.1.0; python_version >= "3.7" and extra == "optional"
Provides-Extra: docs
Requires-Dist: sphinx>=5.0.1; extra == "docs"
Requires-Dist: sphinx-autobuild>=2021.3.14; extra == "docs"
Requires-Dist: sphinx_rtd_theme>=1.0.0; extra == "docs"
Requires-Dist: sphinxcontrib-napoleon>=0.7; extra == "docs"
Requires-Dist: sphinx-autoapi>=1.8.4; extra == "docs"
Requires-Dist: Pygments>=2.9.0; extra == "docs"
Requires-Dist: myst_parser>=0.18.0; extra == "docs"
Requires-Dist: sphinx-reredirects>=0.0.1; extra == "docs"
Provides-Extra: all-strict
Requires-Dist: ubelt==1.3.3; extra == "all-strict"
Requires-Dist: scriptconfig==0.7.10; python_version >= "3.6" and extra == "all-strict"
Requires-Dist: rich==12.4.4; python_version >= "3.8" and extra == "all-strict"
Requires-Dist: rich==11.2.0; (python_version < "3.8" and python_version >= "3.6") and extra == "all-strict"
Requires-Dist: git-python==1.0.0; python_version >= "2.7" and extra == "all-strict"
Requires-Dist: packaging==21.3; extra == "all-strict"
Requires-Dist: networkx==2.8; (python_version < "4.0" and python_version >= "3.11") and extra == "all-strict"
Requires-Dist: networkx==2.7; (python_version < "3.11" and python_version >= "3.8") and extra == "all-strict"
Requires-Dist: networkx==2.6.2; (python_version < "3.8" and python_version >= "3.7") and extra == "all-strict"
Requires-Dist: networkx<=2.5.1,==2.2.0; (python_version < "3.7.0" and python_version >= "3.6.0") and extra == "all-strict"
Requires-Dist: xdoctest==1.1.3; extra == "all-strict"
Requires-Dist: pytest==6.2.5; python_version >= "3.10.0" and extra == "all-strict"
Requires-Dist: pytest==4.6.0; (python_version < "3.10.0" and python_version >= "3.7.0") and extra == "all-strict"
Requires-Dist: pytest==4.6.0; (python_version < "3.7.0" and python_version >= "3.6.0") and extra == "all-strict"
Requires-Dist: pytest<=6.1.2,==4.6.0; (python_version < "3.6.0" and python_version >= "3.5.0") and extra == "all-strict"
Requires-Dist: pytest<=4.6.11,==4.6.0; (python_version < "3.5.0" and python_version >= "3.4.0") and extra == "all-strict"
Requires-Dist: pytest<=4.6.11,==4.6.0; (python_version < "2.8.0" and python_version >= "2.7.0") and extra == "all-strict"
Requires-Dist: pytest-cov==3.0.0; python_version >= "3.6.0" and extra == "all-strict"
Requires-Dist: pytest-cov==2.9.0; (python_version < "3.6.0" and python_version >= "3.5.0") and extra == "all-strict"
Requires-Dist: pytest-cov==2.8.1; (python_version < "3.5.0" and python_version >= "3.4.0") and extra == "all-strict"
Requires-Dist: pytest-cov==2.8.1; (python_version < "2.8.0" and python_version >= "2.7.0") and extra == "all-strict"
Requires-Dist: pytest-timeout==1.4.2; extra == "all-strict"
Requires-Dist: coverage==6.1.1; python_version >= "3.10" and extra == "all-strict"
Requires-Dist: coverage==5.3.1; (python_version < "3.10" and python_version >= "3.9") and extra == "all-strict"
Requires-Dist: coverage==6.1.1; (python_version < "3.9" and python_version >= "3.8") and extra == "all-strict"
Requires-Dist: coverage==6.1.1; (python_version < "3.8" and python_version >= "3.7") and extra == "all-strict"
Requires-Dist: coverage==6.1.1; (python_version < "3.7" and python_version >= "3.6") and extra == "all-strict"
Requires-Dist: coverage==5.3.1; (python_version < "3.6" and python_version >= "3.5") and extra == "all-strict"
Requires-Dist: coverage==4.3.4; (python_version < "3.5" and python_version >= "3.4") and extra == "all-strict"
Requires-Dist: coverage==5.3.1; (python_version < "3.4" and python_version >= "2.7") and extra == "all-strict"
Requires-Dist: coverage==4.5; (python_version < "2.7" and python_version >= "2.6") and extra == "all-strict"
Requires-Dist: argcomplete==1.0; extra == "all-strict"
Requires-Dist: rich_argparse==1.1.0; python_version >= "3.7" and extra == "all-strict"
Provides-Extra: runtime-strict
Requires-Dist: ubelt==1.3.3; extra == "runtime-strict"
Requires-Dist: scriptconfig==0.7.10; python_version >= "3.6" and extra == "runtime-strict"
Requires-Dist: rich==12.4.4; python_version >= "3.8" and extra == "runtime-strict"
Requires-Dist: rich==11.2.0; (python_version < "3.8" and python_version >= "3.6") and extra == "runtime-strict"
Requires-Dist: git-python==1.0.0; python_version >= "2.7" and extra == "runtime-strict"
Requires-Dist: packaging==21.3; extra == "runtime-strict"
Requires-Dist: networkx==2.8; (python_version < "4.0" and python_version >= "3.11") and extra == "runtime-strict"
Requires-Dist: networkx==2.7; (python_version < "3.11" and python_version >= "3.8") and extra == "runtime-strict"
Requires-Dist: networkx==2.6.2; (python_version < "3.8" and python_version >= "3.7") and extra == "runtime-strict"
Requires-Dist: networkx<=2.5.1,==2.2.0; (python_version < "3.7.0" and python_version >= "3.6.0") and extra == "runtime-strict"
Provides-Extra: tests-strict
Requires-Dist: xdoctest==1.1.3; extra == "tests-strict"
Requires-Dist: pytest==6.2.5; python_version >= "3.10.0" and extra == "tests-strict"
Requires-Dist: pytest==4.6.0; (python_version < "3.10.0" and python_version >= "3.7.0") and extra == "tests-strict"
Requires-Dist: pytest==4.6.0; (python_version < "3.7.0" and python_version >= "3.6.0") and extra == "tests-strict"
Requires-Dist: pytest<=6.1.2,==4.6.0; (python_version < "3.6.0" and python_version >= "3.5.0") and extra == "tests-strict"
Requires-Dist: pytest<=4.6.11,==4.6.0; (python_version < "3.5.0" and python_version >= "3.4.0") and extra == "tests-strict"
Requires-Dist: pytest<=4.6.11,==4.6.0; (python_version < "2.8.0" and python_version >= "2.7.0") and extra == "tests-strict"
Requires-Dist: pytest-cov==3.0.0; python_version >= "3.6.0" and extra == "tests-strict"
Requires-Dist: pytest-cov==2.9.0; (python_version < "3.6.0" and python_version >= "3.5.0") and extra == "tests-strict"
Requires-Dist: pytest-cov==2.8.1; (python_version < "3.5.0" and python_version >= "3.4.0") and extra == "tests-strict"
Requires-Dist: pytest-cov==2.8.1; (python_version < "2.8.0" and python_version >= "2.7.0") and extra == "tests-strict"
Requires-Dist: pytest-timeout==1.4.2; extra == "tests-strict"
Requires-Dist: coverage==6.1.1; python_version >= "3.10" and extra == "tests-strict"
Requires-Dist: coverage==5.3.1; (python_version < "3.10" and python_version >= "3.9") and extra == "tests-strict"
Requires-Dist: coverage==6.1.1; (python_version < "3.9" and python_version >= "3.8") and extra == "tests-strict"
Requires-Dist: coverage==6.1.1; (python_version < "3.8" and python_version >= "3.7") and extra == "tests-strict"
Requires-Dist: coverage==6.1.1; (python_version < "3.7" and python_version >= "3.6") and extra == "tests-strict"
Requires-Dist: coverage==5.3.1; (python_version < "3.6" and python_version >= "3.5") and extra == "tests-strict"
Requires-Dist: coverage==4.3.4; (python_version < "3.5" and python_version >= "3.4") and extra == "tests-strict"
Requires-Dist: coverage==5.3.1; (python_version < "3.4" and python_version >= "2.7") and extra == "tests-strict"
Requires-Dist: coverage==4.5; (python_version < "2.7" and python_version >= "2.6") and extra == "tests-strict"
Provides-Extra: optional-strict
Requires-Dist: argcomplete==1.0; extra == "optional-strict"
Requires-Dist: rich_argparse==1.1.0; python_version >= "3.7" and extra == "optional-strict"
Provides-Extra: docs-strict
Requires-Dist: sphinx==5.0.1; extra == "docs-strict"
Requires-Dist: sphinx-autobuild==2021.3.14; extra == "docs-strict"
Requires-Dist: sphinx_rtd_theme==1.0.0; extra == "docs-strict"
Requires-Dist: sphinxcontrib-napoleon==0.7; extra == "docs-strict"
Requires-Dist: sphinx-autoapi==1.8.4; extra == "docs-strict"
Requires-Dist: Pygments==2.9.0; extra == "docs-strict"
Requires-Dist: myst_parser==0.18.0; extra == "docs-strict"
Requires-Dist: sphinx-reredirects==0.0.1; extra == "docs-strict"
Dynamic: author
Dynamic: author-email
Dynamic: classifier
Dynamic: description
Dynamic: description-content-type
Dynamic: home-page
Dynamic: license
Dynamic: provides-extra
Dynamic: requires-dist
Dynamic: requires-python
Dynamic: summary
